README.md
setup.py
clicol_plugin_aspath/__init__.py
clicol_plugin_aspath/asnconvert.py
clicol_plugin_aspath/aspath.py
clicol_plugin_aspath.egg-info/PKG-INFO
clicol_plugin_aspath.egg-info/SOURCES.txt
clicol_plugin_aspath.egg-info/dependency_links.txt
clicol_plugin_aspath.egg-info/entry_points.txt
clicol_plugin_aspath.egg-info/not-zip-safe
clicol_plugin_aspath.egg-info/requires.txt
clicol_plugin_aspath.egg-info/top_level.txt