Metadata-Version: 2.1
Name: clicol-plugin-aspath
Version: 0.0.2
Summary: CLI colorizer - aspath plugin
Home-page: https://github.com/realvitya/clicol_plugin_aspath
Author: Viktor Kertesz
Author-email: vkertesz2@gmail.com
License: GPLv3
Platform: UNKNOWN
Classifier: Development Status :: 4 - Beta
Classifier: Environment :: Console
Classifier: Intended Audience :: Developers
Classifier: Intended Audience :: System Administrators
Classifier: Intended Audience :: Telecommunications Industry
Classifier: License :: OSI Approved :: GNU General Public License v3 (GPLv3)
Classifier: Operating System :: POSIX
Classifier: Programming Language :: Python :: 2.6
Classifier: Programming Language :: Python :: 2.7
Classifier: Programming Language :: Python :: 3
